{
	"info": {
		"_postman_id": "526f0c96-f676-4ae7-8da0-7ea55ed3755c",
		"name": "coffeehouse",
		"schema": "https://schema.getpostman.com/json/collection/v2.1.0/collection.json",
		"_exporter_id": "23786903"
	},
	"item": [
		{
			"name": "Get order",
			"request": {
				"method": "POST",
				"header": [],
				"url": {
					"raw": "http://localhost:8080/events/order/3",
					"protocol": "http",
					"host": [
						"localhost"
					],
					"port": "8080",
					"path": [
						"events",
						"order",
						"3"
					]
				}
			},
			"response": []
		},
		{
			"name": "Registrer event",
			"request": {
				"method": "POST",
				"header": [],
				"body": {
					"mode": "raw",
					"raw": "{\r\n    \"employeeId\": 1,\r\n    \"customerId\": 1,\r\n    \"productId\": 1\r\n}",
					"options": {
						"raw": {
							"language": "json"
						}
					}
				},
				"url": {
					"raw": "http://localhost:8080/events/registration",
					"protocol": "http",
					"host": [
						"localhost"
					],
					"port": "8080",
					"path": [
						"events",
						"registration"
					]
				}
			},
			"response": []
		},
		{
			"name": "Registrer event",
			"request": {
				"method": "POST",
				"header": [],
				"body": {
					"mode": "raw",
					"raw": "{\r\n    \"employeeId\": 1,\r\n    \"customerId\": 3,\r\n    \"productId\": 3\r\n}",
					"options": {
						"raw": {
							"language": "json"
						}
					}
				},
				"url": {
					"raw": "http://localhost:8080/events/registration",
					"protocol": "http",
					"host": [
						"localhost"
					],
					"port": "8080",
					"path": [
						"events",
						"registration"
					]
				}
			},
			"response": []
		},
		{
			"name": "Registrer event",
			"request": {
				"method": "POST",
				"header": [],
				"body": {
					"mode": "raw",
					"raw": "{\r\n    \"employeeId\": 2,\r\n    \"customerId\": 4,\r\n    \"productId\": 2\r\n}",
					"options": {
						"raw": {
							"language": "json"
						}
					}
				},
				"url": {
					"raw": "http://localhost:8080/events/registration",
					"protocol": "http",
					"host": [
						"localhost"
					],
					"port": "8080",
					"path": [
						"events",
						"registration"
					]
				}
			},
			"response": []
		},
		{
			"name": "Order 1 Taken to work event",
			"request": {
				"method": "POST",
				"header": [],
				"body": {
					"mode": "raw",
					"raw": "{\r\n    \"orderId\": 1,\r\n    \"employeeId\": 1\r\n}",
					"options": {
						"raw": {
							"language": "json"
						}
					}
				},
				"url": {
					"raw": "http://localhost:8080/events/taken_to_work",
					"protocol": "http",
					"host": [
						"localhost"
					],
					"port": "8080",
					"path": [
						"events",
						"taken_to_work"
					]
				}
			},
			"response": []
		},
		{
			"name": "Order 2 Taken to work event",
			"request": {
				"method": "POST",
				"header": [],
				"body": {
					"mode": "raw",
					"raw": "{\r\n    \"orderId\": 2,\r\n    \"employeeId\": 1\r\n}",
					"options": {
						"raw": {
							"language": "json"
						}
					}
				},
				"url": {
					"raw": "http://localhost:8080/events/taken_to_work",
					"protocol": "http",
					"host": [
						"localhost"
					],
					"port": "8080",
					"path": [
						"events",
						"taken_to_work"
					]
				}
			},
			"response": []
		},
		{
			"name": "Order 3 Taken to work event",
			"request": {
				"method": "POST",
				"header": [],
				"body": {
					"mode": "raw",
					"raw": "{\r\n    \"orderId\": 3,\r\n    \"employeeId\": 1\r\n}",
					"options": {
						"raw": {
							"language": "json"
						}
					}
				},
				"url": {
					"raw": "http://localhost:8080/events/taken_to_work",
					"protocol": "http",
					"host": [
						"localhost"
					],
					"port": "8080",
					"path": [
						"events",
						"taken_to_work"
					]
				}
			},
			"response": []
		},
		{
			"name": "Order 1 Ready event",
			"request": {
				"method": "POST",
				"header": [],
				"body": {
					"mode": "raw",
					"raw": "{\r\n    \"orderId\": 1,\r\n    \"employeeId\": 1\r\n}",
					"options": {
						"raw": {
							"language": "json"
						}
					}
				},
				"url": {
					"raw": "http://localhost:8080/events/ready",
					"protocol": "http",
					"host": [
						"localhost"
					],
					"port": "8080",
					"path": [
						"events",
						"ready"
					]
				}
			},
			"response": []
		},
		{
			"name": "Order 2 Ready event",
			"request": {
				"method": "POST",
				"header": [],
				"body": {
					"mode": "raw",
					"raw": "{\r\n    \"orderId\": 2,\r\n    \"employeeId\": 1\r\n}",
					"options": {
						"raw": {
							"language": "json"
						}
					}
				},
				"url": {
					"raw": "http://localhost:8080/events/ready",
					"protocol": "http",
					"host": [
						"localhost"
					],
					"port": "8080",
					"path": [
						"events",
						"ready"
					]
				}
			},
			"response": []
		},
		{
			"name": "Order 3 Ready event",
			"request": {
				"method": "POST",
				"header": [],
				"body": {
					"mode": "raw",
					"raw": "{\r\n    \"orderId\": 3,\r\n    \"employeeId\": 1\r\n}",
					"options": {
						"raw": {
							"language": "json"
						}
					}
				},
				"url": {
					"raw": "http://localhost:8080/events/ready",
					"protocol": "http",
					"host": [
						"localhost"
					],
					"port": "8080",
					"path": [
						"events",
						"ready"
					]
				}
			},
			"response": []
		},
		{
			"name": "Order 1 Issued event",
			"request": {
				"method": "POST",
				"header": [],
				"body": {
					"mode": "raw",
					"raw": "{\r\n    \"orderId\": 1,\r\n    \"employeeId\": 2\r\n}",
					"options": {
						"raw": {
							"language": "json"
						}
					}
				},
				"url": {
					"raw": "http://localhost:8080/events/issued",
					"protocol": "http",
					"host": [
						"localhost"
					],
					"port": "8080",
					"path": [
						"events",
						"issued"
					]
				}
			},
			"response": []
		},
		{
			"name": "Order 2 Issued event",
			"request": {
				"method": "POST",
				"header": [],
				"body": {
					"mode": "raw",
					"raw": "{\r\n    \"orderId\": 2,\r\n    \"employeeId\": 1\r\n}",
					"options": {
						"raw": {
							"language": "json"
						}
					}
				},
				"url": {
					"raw": "http://localhost:8080/events/issued",
					"protocol": "http",
					"host": [
						"localhost"
					],
					"port": "8080",
					"path": [
						"events",
						"issued"
					]
				}
			},
			"response": []
		},
		{
			"name": "Order 3 Issued event",
			"request": {
				"method": "POST",
				"header": [],
				"body": {
					"mode": "raw",
					"raw": "{\r\n    \"orderId\": 3,\r\n    \"employeeId\": 2\r\n}",
					"options": {
						"raw": {
							"language": "json"
						}
					}
				},
				"url": {
					"raw": "http://localhost:8080/events/issued",
					"protocol": "http",
					"host": [
						"localhost"
					],
					"port": "8080",
					"path": [
						"events",
						"issued"
					]
				}
			},
			"response": []
		},
		{
			"name": "Order 1 Cancel event",
			"request": {
				"method": "POST",
				"header": [],
				"body": {
					"mode": "raw",
					"raw": "{\r\n    \"orderId\": 1,\r\n    \"employeeId\": 2,\r\n    \"cancelReason\": \"Было лень\"\r\n}",
					"options": {
						"raw": {
							"language": "json"
						}
					}
				},
				"url": {
					"raw": "http://localhost:8080/events/cancel",
					"protocol": "http",
					"host": [
						"localhost"
					],
					"port": "8080",
					"path": [
						"events",
						"cancel"
					]
				}
			},
			"response": []
		},
		{
			"name": "Order 2 Cancel event",
			"request": {
				"method": "POST",
				"header": [],
				"body": {
					"mode": "raw",
					"raw": "{\r\n    \"orderId\": 2,\r\n    \"employeeId\": 1,\r\n    \"cancelReason\": \"Было лень\"\r\n}",
					"options": {
						"raw": {
							"language": "json"
						}
					}
				},
				"url": {
					"raw": "http://localhost:8080/events/cancel",
					"protocol": "http",
					"host": [
						"localhost"
					],
					"port": "8080",
					"path": [
						"events",
						"cancel"
					]
				}
			},
			"response": []
		},
		{
			"name": "Order 3 Cancel event",
			"request": {
				"method": "POST",
				"header": [],
				"body": {
					"mode": "raw",
					"raw": "{\r\n    \"orderId\": 3,\r\n    \"employeeId\": 2,\r\n    \"cancelReason\": \"Было лень\"\r\n}",
					"options": {
						"raw": {
							"language": "json"
						}
					}
				},
				"url": {
					"raw": "http://localhost:8080/events/cancel",
					"protocol": "http",
					"host": [
						"localhost"
					],
					"port": "8080",
					"path": [
						"events",
						"cancel"
					]
				}
			},
			"response": []
		}
	]
}